kjspy/__init__.py
kjspy/src/__init__.py
kjspy/src/kjspy.py
kjspy-0.1.0.dist-info/LICENCE
kjspy-0.1.0.dist-info/METADATA
kjspy-0.1.0.dist-info/WHEEL
kjspy-0.1.0.dist-info/top_level.txt
kjspy-0.1.0.dist-info/RECORD
