Metadata-Version: 2.1
Name: kjspy
Version: 0.1.0
Summary: A Python way to write KubeJS scripts for Minecraft!
Home-page: https://github.com/Bluemethyst/KubePY
Author: ArjanCodes
Author-email: bluemethyst@gmail.com
License: MIT
Classifier: License :: OSI Approved :: MIT License
Classifier: Programming Language :: Python :: 3.10
Classifier: Operating System :: OS Independent
Requires-Python: >=3.10
License-File: LICENCE
